odoo/addons/stock_picking_putinpack_restriction/README.rst
odoo/addons/stock_picking_putinpack_restriction/__init__.py
odoo/addons/stock_picking_putinpack_restriction/__manifest__.py
odoo/addons/stock_picking_putinpack_restriction/i18n/it.po
odoo/addons/stock_picking_putinpack_restriction/i18n/stock_picking_putinpack_restriction.pot
odoo/addons/stock_picking_putinpack_restriction/models/__init__.py
odoo/addons/stock_picking_putinpack_restriction/models/stock_move_line.py
odoo/addons/stock_picking_putinpack_restriction/models/stock_picking.py
odoo/addons/stock_picking_putinpack_restriction/models/stock_picking_type.py
odoo/addons/stock_picking_putinpack_restriction/readme/CONTRIBUTORS.rst
odoo/addons/stock_picking_putinpack_restriction/readme/DESCRIPTION.rst
odoo/addons/stock_picking_putinpack_restriction/readme/USAGE.rst
odoo/addons/stock_picking_putinpack_restriction/static/description/icon.png
odoo/addons/stock_picking_putinpack_restriction/static/description/index.html
odoo/addons/stock_picking_putinpack_restriction/tests/__init__.py
odoo/addons/stock_picking_putinpack_restriction/tests/test_stock_picking_putinpack_restriction.py
odoo/addons/stock_picking_putinpack_restriction/views/stock_picking.xml
odoo/addons/stock_picking_putinpack_restriction/views/stock_picking_type.xml
odoo14_addon_stock_picking_putinpack_restriction-14.0.1.0.1.dist-info/METADATA
odoo14_addon_stock_picking_putinpack_restriction-14.0.1.0.1.dist-info/WHEEL
odoo14_addon_stock_picking_putinpack_restriction-14.0.1.0.1.dist-info/top_level.txt
odoo14_addon_stock_picking_putinpack_restriction-14.0.1.0.1.dist-info/RECORD
